uvlog/__init__.py
uvlog/formatters.py
uvlog/handlers.py
uvlog/py.typed
uvlog/uvlog.py
uvlog-0.1.6.dist-info/LICENSE
uvlog-0.1.6.dist-info/METADATA
uvlog-0.1.6.dist-info/WHEEL
uvlog-0.1.6.dist-info/top_level.txt
uvlog-0.1.6.dist-info/RECORD
